setup.py
bin/jokeByScript
funniest123/__init__.py
funniest123/command_line.py
funniest123/text.py
funniest123.egg-info/PKG-INFO
funniest123.egg-info/SOURCES.txt
funniest123.egg-info/dependency_links.txt
funniest123.egg-info/entry_points.txt
funniest123.egg-info/not-zip-safe
funniest123.egg-info/top_level.txt