Metadata-Version: 1.0
Name: funniest123
Version: 0.2.1
Summary: The funniest joke in the world
Home-page: https://github.com/nickytong/funniest123
Author: nickytong
Author-email: ptong1@mdanderson.org
License: MIT
Platform: UNKNOWN
